syslexer/__init__.py
syslexer/__meta__.py
syslexer/test.py
syslexer-0.1.0.dist-info/METADATA
syslexer-0.1.0.dist-info/WHEEL
syslexer-0.1.0.dist-info/top_level.txt
syslexer-0.1.0.dist-info/RECORD
